momento_redis/__init__.py
momento_redis/momento_redis_client.py
momento_redis/utils/__init__.py
momento_redis/utils/error_utils.py
momento_redis-0.1.2.dist-info/LICENSE
momento_redis-0.1.2.dist-info/METADATA
momento_redis-0.1.2.dist-info/WHEEL
momento_redis-0.1.2.dist-info/RECORD
