Metadata-Version: 2.1
Name: momento-redis
Version: 0.1.2
Summary: Momento wrapper for redis/redis-py
License: Apache-2.0
Author: Momento
Author-email: hello@momentohq.com
Requires-Python: >=3.7,<3.12
Classifier: License :: OSI Approved :: Apache Software License
Classifier: Programming Language :: Python :: 3
Classifier: Programming Language :: Python :: 3.7
Classifier: Programming Language :: Python :: 3.8
Classifier: Programming Language :: Python :: 3.9
Classifier: Programming Language :: Python :: 3.10
Classifier: Programming Language :: Python :: 3.11
Requires-Dist: momento (==1.7.1)
Requires-Dist: redis (==4.6.0)
Requires-Dist: typing-extensions (==4.5.0)
